lincl/__init__.py
lincl-1.0.dist-info/LICENSE
lincl-1.0.dist-info/METADATA
lincl-1.0.dist-info/WHEEL
lincl-1.0.dist-info/top_level.txt
lincl-1.0.dist-info/RECORD
