Metadata-Version: 2.1
Name: lincl
Version: 1.0
Summary: Linux commands line
Home-page: UNKNOWN
Author: Christfried BALIZOU
Author-email: christfriedbalizou@gmail.com
License: MIT
Keywords: subprocess popen check_output check_call dynamicmethods
Platform: UNKNOWN
Classifier: Development Status :: 5 - Production/Stable
Classifier: Intended Audience :: Developers
Classifier: License :: OSI Approved :: MIT License
Classifier: Programming Language :: Python :: 3.7
Requires-Python: >=3.7
Provides-Extra: dev
Requires-Dist: pytest (>=3) ; extra == 'dev'
